{
 "kind": "youtube#searchListResponse",
 "etag": "\"I_8xdZu766_FSaexEaDXTIfEWc0/dJOdUKXgL4iDGG3DzSjiKAj-OnM\"",
 "nextPageToken": "CBQQAA",
 "regionCode": "US",
 "pageInfo": {
  "totalResults": 393403,
  "resultsPerPage": 20
 },
 "items": [
  {
   "kind": "youtube#searchResult",
   "etag": "\"I_8xdZu766_FSaexEaDXTIfEWc0/fKawflrJz-8ngUl34RxhVQ4-OOU\"",
   "id": {
    "kind": "youtube#video",
    "videoId": "_-CD_5YhJTA"
   },
   "snippet": {
    "publishedAt": "2016-03-04T12:12:52.000Z",
    "channelId": "UCWv7vMbMWH4-V0ZXdmDpPBA",
    "title": "Angular 2 Tutorial for Beginners: Learn Angular 2 from Scratch",
    "description": "Want to learn Angular 2 from scratch in a fun, step-by-step and pragmatic way? Watch this tutorial and you'll start coding in just a few minutes. This video is ...",
    "thumbnails": {
     "default": {
      "url": "https://i.ytimg.com/vi/_-CD_5YhJTA/default.jpg",
      "width": 120,
      "height": 90
     },
     "medium": {
      "url": "https://i.ytimg.com/vi/_-CD_5YhJTA/mqdefault.jpg",
      "width": 320,
      "height": 180
     },
     "high": {
      "url": "https://i.ytimg.com/vi/_-CD_5YhJTA/hqdefault.jpg",
      "width": 480,
      "height": 360
     }
    },
    "channelTitle": "Programming with Mosh",
    "liveBroadcastContent": "none"
   }
  },
  {
   "kind": "youtube#searchResult",
   "etag": "\"I_8xdZu766_FSaexEaDXTIfEWc0/P98RhPW1LXXDKQRJ-qIxrMmscLU\"",
   "id": {
    "kind": "youtube#video",
    "videoId": "YAfwASGlLNQ"
   },
   "snippet": {
    "publishedAt": "2016-09-15T13:16:53.000Z",
    "channelId": "UC3cEGKhg3OERn-ihVsJcb7A",
    "title": "Angular 2 Final Release Demo with Angular CLI",
    "description": "This is a demo of the Angular 2 Final release using the Angular CLI webpack preview. we are going to scaffold a project and see how its already an Angular 2 ...",
    "thumbnails": {
     "default": {
      "url": "https://i.ytimg.com/vi/YAfwASGlLNQ/default.jpg",
      "width": 120,
      "height": 90
     },
     "medium": {
      "url": "https://i.ytimg.com/vi/YAfwASGlLNQ/mqdefault.jpg",
      "width": 320,
      "height": 180
     },
     "high": {
      "url": "https://i.ytimg.com/vi/YAfwASGlLNQ/hqdefault.jpg",
      "width": 480,
      "height": 360
     }
    },
    "channelTitle": "Angular University",
    "liveBroadcastContent": "none"
   }
  },
  {
   "kind": "youtube#searchResult",
   "etag": "\"I_8xdZu766_FSaexEaDXTIfEWc0/d9uPSZfT_UQabZeHVSn5wA0iZ08\"",
   "id": {
    "kind": "youtube#video",
    "videoId": "WAPQF_GA7Qg"
   },
   "snippet": {
    "publishedAt": "2016-05-04T17:45:49.000Z",
    "channelId": "UCm9iiIfgmVODUJxINecHQkA",
    "title": "An Angular 2 Force Awakens - John Papa",
    "description": "www.ng-conf.org ng-conf is a two day, single track conference focused on delivering the highest quality training in the Angular JavaScript framework. 500 to 700 ...",
    "thumbnails": {
     "default": {
      "url": "https://i.ytimg.com/vi/WAPQF_GA7Qg/default.jpg",
      "width": 120,
      "height": 90
     },
     "medium": {
      "url": "https://i.ytimg.com/vi/WAPQF_GA7Qg/mqdefault.jpg",
      "width": 320,
      "height": 180
     },
     "high": {
      "url": "https://i.ytimg.com/vi/WAPQF_GA7Qg/hqdefault.jpg",
      "width": 480,
      "height": 360
     }
    },
    "channelTitle": "ng-conf",
    "liveBroadcastContent": "none"
   }
  },
  {
   "kind": "youtube#searchResult",
   "etag": "\"I_8xdZu766_FSaexEaDXTIfEWc0/l2aq45AyPgy-QGjcBW-HQ-KLbCQ\"",
   "id": {
    "kind": "youtube#video",
    "videoId": "DBjPIabiRNg"
   },
   "snippet": {
    "publishedAt": "2016-07-21T15:30:30.000Z",
    "channelId": "UCSJbGtTlrDami-tDGPUV9-w",
    "title": "Angular 2 Tutorial - Complete Introduction - Angular 2 CLI Setup, Components, Databinding",
    "description": "Enjoy this Angular 2 Tutorial, which gives you a complete Introduction Angular 2 - including the Setup with Angular 2 CLI, Components and Databinding.",
    "thumbnails": {
     "default": {
      "url": "https://i.ytimg.com/vi/DBjPIabiRNg/default.jpg",
      "width": 120,
      "height": 90
     },
     "medium": {
      "url": "https://i.ytimg.com/vi/DBjPIabiRNg/mqdefault.jpg",
      "width": 320,
      "height": 180
     },
     "high": {
      "url": "https://i.ytimg.com/vi/DBjPIabiRNg/hqdefault.jpg",
      "width": 480,
      "height": 360
     }
    },
    "channelTitle": "Mindspace",
    "liveBroadcastContent": "none"
   }
  },
  {
   "kind": "youtube#searchResult",
   "etag": "\"I_8xdZu766_FSaexEaDXTIfEWc0/3H-yvapIW2rfM2_kWfnTVBKCLBU\"",
   "id": {
    "kind": "youtube#video",
    "videoId": "RL_2FnIBVgI"
   },
   "snippet": {
    "publishedAt": "2016-09-06T20:35:57.000Z",
    "channelId": "UC29ju8bIPH5as8OGnQzwJyA",
    "title": "Angular 2 Github Application (RC6 Update)",
    "description": "In this video we will build a Github profile search application with Angular 2 RC6. This is an updated version of https://www.youtube.com/watch?v=u83MLQ1VsKI ...",
    "thumbnails": {
     "default": {
      "url": "https://i.ytimg.com/vi/RL_2FnIBVgI/default.jpg",
      "width": 120,
      "height": 90
     },
     "medium": {
      "url": "https://i.ytimg.com/vi/RL_2FnIBVgI/mqdefault.jpg",
      "width": 320,
      "height": 180
     },
     "high": {
      "url": "https://i.ytimg.com/vi/RL_2FnIBVgI/hqdefault.jpg",
      "width": 480,
      "height": 360
     }
    },
    "channelTitle": "Brad Traversy",
    "liveBroadcastContent": "none"
   }
  },
  {
   "kind": "youtube#searchResult",
   "etag": "\"I_8xdZu766_FSaexEaDXTIfEWc0/G-ET79PcvKQXztny28HnAfsBV4M\"",
   "id": {
    "kind": "youtube#video",
    "videoId": "QMQbAoTLJX8"
   },
   "snippet": {
    "publishedAt": "2016-06-15T16:39:29.000Z",
    "channelId": "UC29ju8bIPH5as8OGnQzwJyA",
    "title": "Simple Angular 2 App With Angular CLI",
    "description": "In this video I will show you how to use the Angular-CLI (Command Line Interface) to create an Angular 2 project as well as generate components and services.",
    "thumbnails": {
     "default": {
      "url": "https://i.ytimg.com/vi/QMQbAoTLJX8/default.jpg",
      "width": 120,
      "height": 90
     },
     "medium": {
      "url": "https://i.ytimg.com/vi/QMQbAoTLJX8/mqdefault.jpg",
      "width": 320,
      "height": 180
     },
     "high": {
      "url": "https://i.ytimg.com/vi/QMQbAoTLJX8/hqdefault.jpg",
      "width": 480,
      "height": 360
     }
    },
    "channelTitle": "Brad Traversy",
    "liveBroadcastContent": "none"
   }
  },
  {
   "kind": "youtube#searchResult",
   "etag": "\"I_8xdZu766_FSaexEaDXTIfEWc0/QfR7Hr6FvqunvW5KDV-Z7xkFY0c\"",
   "id": {
    "kind": "youtube#video",
    "videoId": "XlqoPpLMdwY"
   },
   "snippet": {
    "publishedAt": "2016-02-01T22:30:17.000Z",
    "channelId": "UCK9TqOjs5sq2vAu4vUdgyqg",
    "title": "Thinking in Angular 2 - An overview of key Angular 2 concepts for JavaScript developers",
    "description": "Webinar - January 26 2016 Part 2 of http://rangle.io 's Angular 2.0 Series Thinking in Angular 2 - An overview of key Angular 2.0 concepts for Angular 1.0 and ...",
    "thumbnails": {
     "default": {
      "url": "https://i.ytimg.com/vi/XlqoPpLMdwY/default.jpg",
      "width": 120,
      "height": 90
     },
     "medium": {
      "url": "https://i.ytimg.com/vi/XlqoPpLMdwY/mqdefault.jpg",
      "width": 320,
      "height": 180
     },
     "high": {
      "url": "https://i.ytimg.com/vi/XlqoPpLMdwY/hqdefault.jpg",
      "width": 480,
      "height": 360
     }
    },
    "channelTitle": "Rangle.io",
    "liveBroadcastContent": "none"
   }
  },
  {
   "kind": "youtube#searchResult",
   "etag": "\"I_8xdZu766_FSaexEaDXTIfEWc0/nV0u8XJL1RJk3Mei5a1l9MHBGbs\"",
   "id": {
    "kind": "youtube#video",
    "videoId": "EwYD_xqB7Qs"
   },
   "snippet": {
    "publishedAt": "2016-05-25T21:43:40.000Z",
    "channelId": "UCP4bf6IHJJQehibu6ai__cg",
    "title": "Angular 2 - Google I/O 2016",
    "description": "Early on with Angular 2, we focused on creating a full platform that encompasses even more of the needs of our developer community. Mobile is all the rage as ...",
    "thumbnails": {
     "default": {
      "url": "https://i.ytimg.com/vi/EwYD_xqB7Qs/default.jpg",
      "width": 120,
      "height": 90
     },
     "medium": {
      "url": "https://i.ytimg.com/vi/EwYD_xqB7Qs/mqdefault.jpg",
      "width": 320,
      "height": 180
     },
     "high": {
      "url": "https://i.ytimg.com/vi/EwYD_xqB7Qs/hqdefault.jpg",
      "width": 480,
      "height": 360
     }
    },
    "channelTitle": "Firebase",
    "liveBroadcastContent": "none"
   }
  },
  {
   "kind": "youtube#searchResult",
   "etag": "\"I_8xdZu766_FSaexEaDXTIfEWc0/BHr6r6pkC3H2A223aAIeVuCqQwY\"",
   "id": {
    "kind": "youtube#video",
    "videoId": "cxkXHZrcvKY"
   },
   "snippet": {
    "publishedAt": "2016-08-14T22:31:39.000Z",
    "channelId": "UCDS3sAwfomuOa0hRvd9De7A",
    "title": "Angular 2 RC5 - NgModules and Revisiting Forms",
    "description": "Updating ng2play repo to RC5 and talk about NgModules and bumping Material2 to Alpha.7 and Router to RC1. Source code: ...",
    "thumbnails": {
     "default": {
      "url": "https://i.ytimg.com/vi/cxkXHZrcvKY/default.jpg",
      "width": 120,
      "height": 90
     },
     "medium": {
      "url": "https://i.ytimg.com/vi/cxkXHZrcvKY/mqdefault.jpg",
      "width": 320,
      "height": 180
     },
     "high": {
      "url": "https://i.ytimg.com/vi/cxkXHZrcvKY/hqdefault.jpg",
      "width": 480,
      "height": 360
     }
    },
    "channelTitle": "Ajden Towfeek",
    "liveBroadcastContent": "none"
   }
  },
  {
   "kind": "youtube#searchResult",
   "etag": "\"I_8xdZu766_FSaexEaDXTIfEWc0/odJJ9JztzRPWOOGntJK3xjVBenU\"",
   "id": {
    "kind": "youtube#video",
    "videoId": "W14_ZArh6eo"
   },
   "snippet": {
    "publishedAt": "2016-01-04T17:26:06.000Z",
    "channelId": "UCLXQoK41TOcIsWtY-BgB_kQ",
    "title": "Angular 2 Quickstart Tutorial 2016",
    "description": "In this video you will learn how to get started with a basic Angular 2 (Beta) project very quickly. It takes you through the basic steps of setting up a project, ...",
    "thumbnails": {
     "default": {
      "url": "https://i.ytimg.com/vi/W14_ZArh6eo/default.jpg",
      "width": 120,
      "height": 90
     },
     "medium": {
      "url": "https://i.ytimg.com/vi/W14_ZArh6eo/mqdefault.jpg",
      "width": 320,
      "height": 180
     },
     "high": {
      "url": "https://i.ytimg.com/vi/W14_ZArh6eo/hqdefault.jpg",
      "width": 480,
      "height": 360
     }
    },
    "channelTitle": "CodingTheSmartWay.com",
    "liveBroadcastContent": "none"
   }
  },
  {
   "kind": "youtube#searchResult",
   "etag": "\"I_8xdZu766_FSaexEaDXTIfEWc0/mQ5kdUHmWbZpJbi2C4Yaz07bE6Q\"",
   "id": {
    "kind": "youtube#video",
    "videoId": "e3djIqAGqZo"
   },
   "snippet": {
    "publishedAt": "2016-05-04T17:53:58.000Z",
    "channelId": "UCm9iiIfgmVODUJxINecHQkA",
    "title": "Typescript: Angular 2's Secret Weapon - Dan Wahlin",
    "description": "www.ng-conf.org ng-conf is a two day, single track conference focused on delivering the highest quality training in the Angular JavaScript framework. 500 to 700 ...",
    "thumbnails": {
     "default": {
      "url": "https://i.ytimg.com/vi/e3djIqAGqZo/default.jpg",
      "width": 120,
      "height": 90
     },
     "medium": {
      "url": "https://i.ytimg.com/vi/e3djIqAGqZo/mqdefault.jpg",
      "width": 320,
      "height": 180
     },
     "high": {
      "url": "https://i.ytimg.com/vi/e3djIqAGqZo/hqdefault.jpg",
      "width": 480,
      "height": 360
     }
    },
    "channelTitle": "ng-conf",
    "liveBroadcastContent": "none"
   }
  },
  {
   "kind": "youtube#searchResult",
   "etag": "\"I_8xdZu766_FSaexEaDXTIfEWc0/3j-uS-F-Y-9sMd24T0RwgJaN3yI\"",
   "id": {
    "kind": "youtube#video",
    "videoId": "vAb-2d1vcg8"
   },
   "snippet": {
    "publishedAt": "2016-05-19T05:10:18.000Z",
    "channelId": "UCP4bf6IHJJQehibu6ai__cg",
    "title": "Angular 2 and Progressive Web Apps - Google I/O 2016",
    "description": "The Angular team has been investing in building tools and techniques that enable large teams to build robust applications that span desktop and mobile.",
    "thumbnails": {
     "default": {
      "url": "https://i.ytimg.com/vi/vAb-2d1vcg8/default.jpg",
      "width": 120,
      "height": 90
     },
     "medium": {
      "url": "https://i.ytimg.com/vi/vAb-2d1vcg8/mqdefault.jpg",
      "width": 320,
      "height": 180
     },
     "high": {
      "url": "https://i.ytimg.com/vi/vAb-2d1vcg8/hqdefault.jpg",
      "width": 480,
      "height": 360
     }
    },
    "channelTitle": "Firebase",
    "liveBroadcastContent": "none"
   }
  },
  {
   "kind": "youtube#searchResult",
   "etag": "\"I_8xdZu766_FSaexEaDXTIfEWc0/uLyyf23h3th67Eh8OoPcYScUX6I\"",
   "id": {
    "kind": "youtube#video",
    "videoId": "hXfigUyeHaY"
   },
   "snippet": {
    "publishedAt": "2016-04-04T14:32:46.000Z",
    "channelId": "UCJbPGzawDH1njbqV-D5HqKw",
    "title": "Angular 2 for Beginners - Tutorial 1 - Getting Started",
    "description": "Facebook - https://www.facebook.com/TheNewBoston-464114846956315/ GitHub - https://github.com/buckyroberts Google+ ...",
    "thumbnails": {
     "default": {
      "url": "https://i.ytimg.com/vi/hXfigUyeHaY/default.jpg",
      "width": 120,
      "height": 90
     },
     "medium": {
      "url": "https://i.ytimg.com/vi/hXfigUyeHaY/mqdefault.jpg",
      "width": 320,
      "height": 180
     },
     "high": {
      "url": "https://i.ytimg.com/vi/hXfigUyeHaY/hqdefault.jpg",
      "width": 480,
      "height": 360
     }
    },
    "channelTitle": "thenewboston",
    "liveBroadcastContent": "none"
   }
  },
  {
   "kind": "youtube#searchResult",
   "etag": "\"I_8xdZu766_FSaexEaDXTIfEWc0/uk9JASKc7jSJEF-JhHG-17sG-cY\"",
   "id": {
    "kind": "youtube#video",
    "videoId": "Y7izsxhPpQY"
   },
   "snippet": {
    "publishedAt": "2016-06-07T01:29:25.000Z",
    "channelId": "UCQZyH9sRRjvtZhMw-ldRvXQ",
    "title": "Angular 2 primeros pasos",
    "description": "Qué es Angular 2, cuáles son sus novedades con respecto a la versión anterior y cómo iniciarse en la construcción de aplicaciones web con Angular 2.",
    "thumbnails": {
     "default": {
      "url": "https://i.ytimg.com/vi/Y7izsxhPpQY/default.jpg",
      "width": 120,
      "height": 90
     },
     "medium": {
      "url": "https://i.ytimg.com/vi/Y7izsxhPpQY/mqdefault.jpg",
      "width": 320,
      "height": 180
     },
     "high": {
      "url": "https://i.ytimg.com/vi/Y7izsxhPpQY/hqdefault.jpg",
      "width": 480,
      "height": 360
     }
    },
    "channelTitle": "DesarrolloWeb.com",
    "liveBroadcastContent": "none"
   }
  },
  {
   "kind": "youtube#searchResult",
   "etag": "\"I_8xdZu766_FSaexEaDXTIfEWc0/-ZsuntOAoZKJo6hkCUbeCyJW4eU\"",
   "id": {
    "kind": "youtube#video",
    "videoId": "w1PFJT_FfSY"
   },
   "snippet": {
    "publishedAt": "2016-07-05T12:28:11.000Z",
    "channelId": "UCDS3sAwfomuOa0hRvd9De7A",
    "title": "Angular 2 NEW 3.0 Router - Guarding Routes with an Authentication Guard",
    "description": "In this episode we upgrade the ng2play repo to leverage the new 3.0 router and implement a route guard to protect components that require authentication.",
    "thumbnails": {
     "default": {
      "url": "https://i.ytimg.com/vi/w1PFJT_FfSY/default.jpg",
      "width": 120,
      "height": 90
     },
     "medium": {
      "url": "https://i.ytimg.com/vi/w1PFJT_FfSY/mqdefault.jpg",
      "width": 320,
      "height": 180
     },
     "high": {
      "url": "https://i.ytimg.com/vi/w1PFJT_FfSY/hqdefault.jpg",
      "width": 480,
      "height": 360
     }
    },
    "channelTitle": "Ajden Towfeek",
    "liveBroadcastContent": "none"
   }
  },
  {
   "kind": "youtube#searchResult",
   "etag": "\"I_8xdZu766_FSaexEaDXTIfEWc0/iaRIDxVKzjxganMJZ0Hpgy9IIiU\"",
   "id": {
    "kind": "youtube#video",
    "videoId": "VzSg-VrifVU"
   },
   "snippet": {
    "publishedAt": "2016-02-15T22:12:25.000Z",
    "channelId": "UChbgq97Sm-w9OMXQ_Scz8AA",
    "title": "Curso Angular 2 - Aula 1 - Criando a primeira aplicação",
    "description": "Primeiro curso em português de Angular 2! Acesse o curso completo com material de apoio em http://kazale.com Curso 100% gratuito! Aula 1 - Vamos começar ...",
    "thumbnails": {
     "default": {
      "url": "https://i.ytimg.com/vi/VzSg-VrifVU/default.jpg",
      "width": 120,
      "height": 90
     },
     "medium": {
      "url": "https://i.ytimg.com/vi/VzSg-VrifVU/mqdefault.jpg",
      "width": 320,
      "height": 180
     },
     "high": {
      "url": "https://i.ytimg.com/vi/VzSg-VrifVU/hqdefault.jpg",
      "width": 480,
      "height": 360
     }
    },
    "channelTitle": "Márcio Souza",
    "liveBroadcastContent": "none"
   }
  },
  {
   "kind": "youtube#searchResult",
   "etag": "\"I_8xdZu766_FSaexEaDXTIfEWc0/d6CNdY2AR2en-JA-bTTxHWdL6dg\"",
   "id": {
    "kind": "youtube#video",
    "videoId": "Yfebo2mFrTU"
   },
   "snippet": {
    "publishedAt": "2016-09-05T14:25:05.000Z",
    "channelId": "UC3cEGKhg3OERn-ihVsJcb7A",
    "title": "Angular 2 Forms Course Sample -  Covers Angular 2 Final Release",
    "description": "This is a 28 minute sample of the full Angular 2 Forms Course from the Angular University - https://angular-university.io/course/angular2-forms Its made of of the ...",
    "thumbnails": {
     "default": {
      "url": "https://i.ytimg.com/vi/Yfebo2mFrTU/default.jpg",
      "width": 120,
      "height": 90
     },
     "medium": {
      "url": "https://i.ytimg.com/vi/Yfebo2mFrTU/mqdefault.jpg",
      "width": 320,
      "height": 180
     },
     "high": {
      "url": "https://i.ytimg.com/vi/Yfebo2mFrTU/hqdefault.jpg",
      "width": 480,
      "height": 360
     }
    },
    "channelTitle": "Angular University",
    "liveBroadcastContent": "none"
   }
  },
  {
   "kind": "youtube#searchResult",
   "etag": "\"I_8xdZu766_FSaexEaDXTIfEWc0/LytaNIdil6Z04EfFbgKtJn53aKs\"",
   "id": {
    "kind": "youtube#video",
    "videoId": "FIqXDNNBVv0"
   },
   "snippet": {
    "publishedAt": "2016-09-03T18:19:38.000Z",
    "channelId": "UC3cEGKhg3OERn-ihVsJcb7A",
    "title": "Angular 2 Final Release - NgModule",
    "description": "In this lesson we are going give an introduction to Angular 2 modularity and the @NgModule annotation. We are going to learn what is a feature module and in ...",
    "thumbnails": {
     "default": {
      "url": "https://i.ytimg.com/vi/FIqXDNNBVv0/default.jpg",
      "width": 120,
      "height": 90
     },
     "medium": {
      "url": "https://i.ytimg.com/vi/FIqXDNNBVv0/mqdefault.jpg",
      "width": 320,
      "height": 180
     },
     "high": {
      "url": "https://i.ytimg.com/vi/FIqXDNNBVv0/hqdefault.jpg",
      "width": 480,
      "height": 360
     }
    },
    "channelTitle": "Angular University",
    "liveBroadcastContent": "none"
   }
  },
  {
   "kind": "youtube#searchResult",
   "etag": "\"I_8xdZu766_FSaexEaDXTIfEWc0/AwXPa8EwZPPNBUktbZq2AmeshDc\"",
   "id": {
    "kind": "youtube#video",
    "videoId": "1lBxgACVcrQ"
   },
   "snippet": {
    "publishedAt": "2016-05-23T16:45:06.000Z",
    "channelId": "UCbrXRQHV4TOU4Pqzw325Z1A",
    "title": "Angular 2 force awakens with John Papa - Webinar Recording",
    "description": "Pluralsight author and Google Developer Expert, John Papa, guides attendees in this recorded webinar event. John covers the 7 fundamentals of Angular 2, ...",
    "thumbnails": {
     "default": {
      "url": "https://i.ytimg.com/vi/1lBxgACVcrQ/default.jpg",
      "width": 120,
      "height": 90
     },
     "medium": {
      "url": "https://i.ytimg.com/vi/1lBxgACVcrQ/mqdefault.jpg",
      "width": 320,
      "height": 180
     },
     "high": {
      "url": "https://i.ytimg.com/vi/1lBxgACVcrQ/hqdefault.jpg",
      "width": 480,
      "height": 360
     }
    },
    "channelTitle": "Pluralsight",
    "liveBroadcastContent": "none"
   }
  },
  {
   "kind": "youtube#searchResult",
   "etag": "\"I_8xdZu766_FSaexEaDXTIfEWc0/JIyvNyy9mw54qTLnDEzR4_sorE8\"",
   "id": {
    "kind": "youtube#video",
    "videoId": "OpS2R7rbpRg"
   },
   "snippet": {
    "publishedAt": "2016-05-10T19:25:28.000Z",
    "channelId": "UCQZyH9sRRjvtZhMw-ldRvXQ",
    "title": "Qué lenguaje usar para desarrollar en Angular 2",
    "description": "Desarrollar con Angular 2. Alternativas de lenguajes basados en Javascript. Es una discusión entre desarrolladores sobre cuál es el mejor lenguaje para ...",
    "thumbnails": {
     "default": {
      "url": "https://i.ytimg.com/vi/OpS2R7rbpRg/default.jpg",
      "width": 120,
      "height": 90
     },
     "medium": {
      "url": "https://i.ytimg.com/vi/OpS2R7rbpRg/mqdefault.jpg",
      "width": 320,
      "height": 180
     },
     "high": {
      "url": "https://i.ytimg.com/vi/OpS2R7rbpRg/hqdefault.jpg",
      "width": 480,
      "height": 360
     }
    },
    "channelTitle": "DesarrolloWeb.com",
    "liveBroadcastContent": "none"
   }
  }
 ]
}
